google_images_search/__init__.py
google_images_search/cli.py
google_images_search/fetch_resize_save.py
google_images_search/google_api.py
google_images_search/meta.py
Google_Images_Search-1.4.6.dist-info/LICENSE
Google_Images_Search-1.4.6.dist-info/METADATA
Google_Images_Search-1.4.6.dist-info/WHEEL
Google_Images_Search-1.4.6.dist-info/entry_points.txt
Google_Images_Search-1.4.6.dist-info/top_level.txt
Google_Images_Search-1.4.6.dist-info/RECORD
