Metadata-Version: 2.1
Name: Google-Images-Search
Version: 1.4.6
Summary: Search for image using Google Custom Search API and resize & crop the image afterwords
Home-page: https://github.com/arrrlo/Google-Images-Search
Author: Ivan Arar
Author-email: ivan.arar@gmail.com
License: MIT
Project-URL: Source, https://github.com/arrrlo/Google-Images-Search
Keywords: google images,resize,crop
Classifier: Development Status :: 5 - Production/Stable
Classifier: Intended Audience :: Developers
Classifier: Topic :: Software Development :: Build Tools
Classifier: License :: OSI Approved :: MIT License
Classifier: Programming Language :: Python :: 3.7
Classifier: Programming Language :: Python :: 3.8
Classifier: Programming Language :: Python :: 3.9
License-File: LICENSE
